datasette_redirect_to_https/__init__.py
datasette_redirect_to_https-0.2.dist-info/METADATA
datasette_redirect_to_https-0.2.dist-info/WHEEL
datasette_redirect_to_https-0.2.dist-info/entry_points.txt
datasette_redirect_to_https-0.2.dist-info/top_level.txt
datasette_redirect_to_https-0.2.dist-info/RECORD
