Metadata-Version: 2.1
Name: datasette-redirect-to-https
Version: 0.2
Summary: Datasette plugin that redirects all non-https requests to https
Home-page: https://github.com/simonw/datasette-redirect-to-https
Author: Simon Willison
License: Apache License, Version 2.0
Project-URL: Issues, https://github.com/simonw/datasette-redirect-to-https/issues
Project-URL: CI, https://github.com/simonw/datasette-redirect-to-https/actions
Project-URL: Changelog, https://github.com/simonw/datasette-redirect-to-https/releases
Requires-Python: >=3.6
Requires-Dist: datasette
Provides-Extra: test
Requires-Dist: pytest ; extra == 'test'
Requires-Dist: pytest-asyncio ; extra == 'test'
Requires-Dist: asgi-lifespan ; extra == 'test'
